hpalette/__init__.py
hpalette/seas.py
hpalette-0.1.0.dist-info/LICENSE
hpalette-0.1.0.dist-info/METADATA
hpalette-0.1.0.dist-info/WHEEL
hpalette-0.1.0.dist-info/top_level.txt
hpalette-0.1.0.dist-info/RECORD
