Metadata-Version: 2.1
Name: hpalette
Version: 0.1.0
Summary: Library of color palettes for Harvard identity guidelines.
Home-page: https://github.com/saketh/hpalette
Author: Saketh Rama
Author-email: rama@seas.harvard.edu
License: UNKNOWN
Platform: UNKNOWN
Classifier: Programming Language :: Python
Classifier: Intended Audience :: Education
Classifier: Topic :: Multimedia :: Graphics
Classifier: License :: OSI Approved :: MIT License
Classifier: Operating System :: OS Independent
